[{"code_id":"askall","code_value":"Questions 1~2 You want to lose weight. Ask the fitness coach two questions about it.</br>Questions 3~4 You are going to college. Ask one of your relatives who is a college student about the life in college.","code_class":"","code_type":"txt"},{"code_id":"ask1","code_value":"Questions 1~2 You want to lose weight. Ask the fitness coach two questions about it.","code_class":"","code_type":"txt"},{"code_id":"ask2","code_value":"Questions 3~4 You are going to college. Ask one of your relatives who is a college student about the life in college.","code_class":"","code_type":"txt"}]